clilib/__init__.py
clilib/decorator.py
clilib/verb.py
clilib/base/__init__.py
clilib/base/base_resource.py
clilib/decorator/__init__.py
clilib/decorator/arg.py
clilib/decorator/resource.py
clilib/decorator/util.py
clilib/decorator/verb.py
clilib/munge/__init__.py
clilib/munge/kebab.py
clilib/util/__init__.py
tests/__init__.py
tests/test_verb.py
pyclilib-0.3.1.dist-info/LICENSE
pyclilib-0.3.1.dist-info/METADATA
pyclilib-0.3.1.dist-info/WHEEL
pyclilib-0.3.1.dist-info/top_level.txt
pyclilib-0.3.1.dist-info/RECORD
