Metadata-Version: 2.1
Name: pyclilib
Version: 0.3.1
Summary: Build CLI Tools with ease
Home-page: https://github.com/markediez/clilib
Author: Mark Diez
Author-email: markediez@gmail.com
License: UNKNOWN
Platform: UNKNOWN
Classifier: Programming Language :: Python :: 3
Classifier: License :: OSI Approved :: MIT License
Classifier: Operating System :: OS Independent
Requires-Python: >=3.6
Requires-Dist: pylogrus
